{
  "pshenmic": "2025-01-26",
  "vivekgsharma": "2026-05-18",
  "ZocoLini": "2026-04-08",
  "Inna333-cuber": "2025-03-16",
  "llbartekll": "2026-04-13",
  "QuantumExplorer": "2024-05-01",
  "densmirnov": "2026-06-03",
  "pauldelucia": "2026-01-10",
  "DashBot-0001": "2026-06-07",
  "ktechmidas": "2026-02-26",
  "lklimek": "2025-06-24",
  "Claudius-Maginificent": "2026-04-27",
  "PastaPastaPasta": "2026-01-13",
  "shumkov": "2024-07-31",
  "thepastaclaw": "2026-02-17",
  "thephez": "2026-04-09",
  "ogabrielides": "2025-03-07"
}