{
  "date": "2026-06-06",
  "summary": {
    "open_prs": 50,
    "prs_needing_author_action": 16,
    "total_unresolved": 122
  },
  "per_author": [
    {
      "login": "QuantumExplorer",
      "total_open_prs": 11,
      "clean_prs": 1,
      "dirty_prs": 4,
      "deferred_prs": 2,
      "draft_prs": 2,
      "stale_prs": 1,
      "ci_failing_prs": 0,
      "changes_requested_prs": 1,
      "awaiting_review": 1,
      "prs_needing_author_action": 5,
      "total_unresolved": 26,
      "total_score": 190.49154297362088,
      "oldest_stale_pr_days": 38.539791666666666
    },
    {
      "login": "PastaPastaPasta",
      "total_open_prs": 12,
      "clean_prs": 0,
      "dirty_prs": 4,
      "deferred_prs": 0,
      "draft_prs": 6,
      "stale_prs": 2,
      "ci_failing_prs": 0,
      "changes_requested_prs": 0,
      "awaiting_review": 0,
      "prs_needing_author_action": 4,
      "total_unresolved": 14,
      "total_score": 123.26876521175666,
      "oldest_stale_pr_days": 34.13814814814815
    },
    {
      "login": "lklimek",
      "total_open_prs": 14,
      "clean_prs": 0,
      "dirty_prs": 4,
      "deferred_prs": 5,
      "draft_prs": 1,
      "stale_prs": 4,
      "ci_failing_prs": 0,
      "changes_requested_prs": 0,
      "awaiting_review": 0,
      "prs_needing_author_action": 3,
      "total_unresolved": 51,
      "total_score": 299.13439210759464,
      "oldest_stale_pr_days": 7.619884259259259
    },
    {
      "login": "llbartekll",
      "total_open_prs": 2,
      "clean_prs": 0,
      "dirty_prs": 2,
      "deferred_prs": 0,
      "draft_prs": 0,
      "stale_prs": 0,
      "ci_failing_prs": 0,
      "changes_requested_prs": 0,
      "awaiting_review": 2,
      "prs_needing_author_action": 2,
      "total_unresolved": 3,
      "total_score": 25.20554089834891,
      "oldest_stale_pr_days": 4.368680555555556
    },
    {
      "login": "ZocoLini",
      "total_open_prs": 6,
      "clean_prs": 2,
      "dirty_prs": 1,
      "deferred_prs": 0,
      "draft_prs": 2,
      "stale_prs": 0,
      "ci_failing_prs": 0,
      "changes_requested_prs": 1,
      "awaiting_review": 0,
      "prs_needing_author_action": 2,
      "total_unresolved": 23,
      "total_score": 141.45418138569426,
      "oldest_stale_pr_days": 10.150416666666667
    },
    {
      "login": "pshenmic",
      "total_open_prs": 1,
      "clean_prs": 0,
      "dirty_prs": 0,
      "deferred_prs": 0,
      "draft_prs": 0,
      "stale_prs": 1,
      "ci_failing_prs": 0,
      "changes_requested_prs": 0,
      "awaiting_review": 0,
      "prs_needing_author_action": 0,
      "total_unresolved": 5,
      "total_score": 117.82345522741196,
      "oldest_stale_pr_days": 492.35770833333333
    },
    {
      "login": "ogabrielides",
      "total_open_prs": 1,
      "clean_prs": 0,
      "dirty_prs": 0,
      "deferred_prs": 1,
      "draft_prs": 0,
      "stale_prs": 0,
      "ci_failing_prs": 0,
      "changes_requested_prs": 0,
      "awaiting_review": 0,
      "prs_needing_author_action": 0,
      "total_unresolved": 0,
      "total_score": 0.0,
      "oldest_stale_pr_days": 0.0
    },
    {
      "login": "shumkov",
      "total_open_prs": 3,
      "clean_prs": 0,
      "dirty_prs": 0,
      "deferred_prs": 2,
      "draft_prs": 0,
      "stale_prs": 0,
      "ci_failing_prs": 1,
      "changes_requested_prs": 0,
      "awaiting_review": 0,
      "prs_needing_author_action": 0,
      "total_unresolved": 0,
      "total_score": 0.0,
      "oldest_stale_pr_days": 0.0
    }
  ],
  "per_pr": [
    {
      "number": 3800,
      "author": "QuantumExplorer",
      "score": 0.0,
      "unresolved_total": 0,
      "by_severity": {
        "high": 0,
        "medium": 0,
        "low": 0
      },
      "by_source": {
        "coderabbit": 0,
        "bot": 0,
        "human": 0
      },
      "needs_author_action": true
    },
    {
      "number": 3785,
      "author": "ZocoLini",
      "score": 0.0,
      "unresolved_total": 0,
      "by_severity": {
        "high": 0,
        "medium": 0,
        "low": 0
      },
      "by_source": {
        "coderabbit": 0,
        "bot": 0,
        "human": 0
      },
      "needs_author_action": false
    },
    {
      "number": 3573,
      "author": "shumkov",
      "score": 0.0,
      "unresolved_total": 0,
      "by_severity": {
        "high": 0,
        "medium": 0,
        "low": 0
      },
      "by_source": {
        "coderabbit": 0,
        "bot": 0,
        "human": 0
      },
      "needs_author_action": false
    },
    {
      "number": 3777,
      "author": "ZocoLini",
      "score": 4.0,
      "unresolved_total": 2,
      "by_severity": {
        "high": 0,
        "medium": 2,
        "low": 0
      },
      "by_source": {
        "coderabbit": 0,
        "bot": 0,
        "human": 2
      },
      "needs_author_action": true
    },
    {
      "number": 3792,
      "author": "QuantumExplorer",
      "score": 6.0,
      "unresolved_total": 3,
      "by_severity": {
        "high": 0,
        "medium": 3,
        "low": 0
      },
      "by_source": {
        "coderabbit": 0,
        "bot": 0,
        "human": 3
      },
      "needs_author_action": false
    },
    {
      "number": 3793,
      "author": "QuantumExplorer",
      "score": 8.0,
      "unresolved_total": 4,
      "by_severity": {
        "high": 0,
        "medium": 4,
        "low": 0
      },
      "by_source": {
        "coderabbit": 0,
        "bot": 0,
        "human": 4
      },
      "needs_author_action": true
    },
    {
      "number": 3799,
      "author": "QuantumExplorer",
      "score": 0.0,
      "unresolved_total": 0,
      "by_severity": {
        "high": 0,
        "medium": 0,
        "low": 0
      },
      "by_source": {
        "coderabbit": 0,
        "bot": 0,
        "human": 0
      },
      "needs_author_action": false
    },
    {
      "number": 3625,
      "author": "Claudius-Maginificent",
      "score": 70.24075757803021,
      "unresolved_total": 16,
      "by_severity": {
        "high": 5,
        "medium": 11,
        "low": 0
      },
      "by_source": {
        "coderabbit": 5,
        "bot": 0,
        "human": 11
      },
      "needs_author_action": false
    },
    {
      "number": 3788,
      "author": "ZocoLini",
      "score": 0.0,
      "unresolved_total": 0,
      "by_severity": {
        "high": 0,
        "medium": 0,
        "low": 0
      },
      "by_source": {
        "coderabbit": 0,
        "bot": 0,
        "human": 0
      },
      "needs_author_action": false
    },
    {
      "number": 3692,
      "author": "Claudius-Maginificent",
      "score": 0.0,
      "unresolved_total": 0,
      "by_severity": {
        "high": 0,
        "medium": 0,
        "low": 0
      },
      "by_source": {
        "coderabbit": 0,
        "bot": 0,
        "human": 0
      },
      "needs_author_action": false
    },
    {
      "number": 3727,
      "author": "lklimek",
      "score": 0.0,
      "unresolved_total": 0,
      "by_severity": {
        "high": 0,
        "medium": 0,
        "low": 0
      },
      "by_source": {
        "coderabbit": 0,
        "bot": 0,
        "human": 0
      },
      "needs_author_action": false
    },
    {
      "number": 3778,
      "author": "ZocoLini",
      "score": 0.0,
      "unresolved_total": 0,
      "by_severity": {
        "high": 0,
        "medium": 0,
        "low": 0
      },
      "by_source": {
        "coderabbit": 0,
        "bot": 0,
        "human": 0
      },
      "needs_author_action": false
    },
    {
      "number": 3784,
      "author": "QuantumExplorer",
      "score": 0.0,
      "unresolved_total": 0,
      "by_severity": {
        "high": 0,
        "medium": 0,
        "low": 0
      },
      "by_source": {
        "coderabbit": 0,
        "bot": 0,
        "human": 0
      },
      "needs_author_action": false
    },
    {
      "number": 3781,
      "author": "Claudius-Maginificent",
      "score": 37.0417575136629,
      "unresolved_total": 8,
      "by_severity": {
        "high": 3,
        "medium": 5,
        "low": 0
      },
      "by_source": {
        "coderabbit": 3,
        "bot": 0,
        "human": 5
      },
      "needs_author_action": true
    },
    {
      "number": 3750,
      "author": "Claudius-Maginificent",
      "score": 0.0,
      "unresolved_total": 0,
      "by_severity": {
        "high": 0,
        "medium": 0,
        "low": 0
      },
      "by_source": {
        "coderabbit": 0,
        "bot": 0,
        "human": 0
      },
      "needs_author_action": false
    },
    {
      "number": 3650,
      "author": "lklimek",
      "score": 17.232573260682983,
      "unresolved_total": 4,
      "by_severity": {
        "high": 0,
        "medium": 4,
        "low": 0
      },
      "by_source": {
        "coderabbit": 0,
        "bot": 0,
        "human": 4
      },
      "needs_author_action": true
    },
    {
      "number": 3549,
      "author": "Claudius-Maginificent",
      "score": 142.3525839603771,
      "unresolved_total": 20,
      "by_severity": {
        "high": 0,
        "medium": 20,
        "low": 0
      },
      "by_source": {
        "coderabbit": 0,
        "bot": 0,
        "human": 20
      },
      "needs_author_action": false
    },
    {
      "number": 3462,
      "author": "PastaPastaPasta",
      "score": 10.098298378664078,
      "unresolved_total": 3,
      "by_severity": {
        "high": 0,
        "medium": 3,
        "low": 0
      },
      "by_source": {
        "coderabbit": 0,
        "bot": 0,
        "human": 3
      },
      "needs_author_action": true
    },
    {
      "number": 3680,
      "author": "PastaPastaPasta",
      "score": 24.161669291260452,
      "unresolved_total": 5,
      "by_severity": {
        "high": 0,
        "medium": 5,
        "low": 0
      },
      "by_source": {
        "coderabbit": 0,
        "bot": 0,
        "human": 5
      },
      "needs_author_action": true
    },
    {
      "number": 3772,
      "author": "QuantumExplorer",
      "score": 10.823251232372005,
      "unresolved_total": 3,
      "by_severity": {
        "high": 0,
        "medium": 3,
        "low": 0
      },
      "by_source": {
        "coderabbit": 1,
        "bot": 0,
        "human": 2
      },
      "needs_author_action": true
    },
    {
      "number": 3639,
      "author": "ZocoLini",
      "score": 0.0,
      "unresolved_total": 0,
      "by_severity": {
        "high": 0,
        "medium": 0,
        "low": 0
      },
      "by_source": {
        "coderabbit": 0,
        "bot": 0,
        "human": 0
      },
      "needs_author_action": true
    },
    {
      "number": 3712,
      "author": "ZocoLini",
      "score": 137.45418138569426,
      "unresolved_total": 21,
      "by_severity": {
        "high": 5,
        "medium": 16,
        "low": 0
      },
      "by_source": {
        "coderabbit": 5,
        "bot": 0,
        "human": 16
      },
      "needs_author_action": false
    },
    {
      "number": 3133,
      "author": "thepastaclaw",
      "score": 0.0,
      "unresolved_total": 0,
      "by_severity": {
        "high": 0,
        "medium": 0,
        "low": 0
      },
      "by_source": {
        "coderabbit": 0,
        "bot": 0,
        "human": 0
      },
      "needs_author_action": false
    },
    {
      "number": 3669,
      "author": "thepastaclaw",
      "score": 0.0,
      "unresolved_total": 0,
      "by_severity": {
        "high": 0,
        "medium": 0,
        "low": 0
      },
      "by_source": {
        "coderabbit": 0,
        "bot": 0,
        "human": 0
      },
      "needs_author_action": false
    },
    {
      "number": 3694,
      "author": "llbartekll",
      "score": 8.39971918105385,
      "unresolved_total": 1,
      "by_severity": {
        "high": 1,
        "medium": 0,
        "low": 0
      },
      "by_source": {
        "coderabbit": 0,
        "bot": 0,
        "human": 1
      },
      "needs_author_action": true
    },
    {
      "number": 3560,
      "author": "llbartekll",
      "score": 16.80582171729506,
      "unresolved_total": 2,
      "by_severity": {
        "high": 2,
        "medium": 0,
        "low": 0
      },
      "by_source": {
        "coderabbit": 0,
        "bot": 0,
        "human": 2
      },
      "needs_author_action": true
    },
    {
      "number": 3585,
      "author": "Claudius-Maginificent",
      "score": 32.266719794841386,
      "unresolved_total": 3,
      "by_severity": {
        "high": 3,
        "medium": 0,
        "low": 0
      },
      "by_source": {
        "coderabbit": 0,
        "bot": 0,
        "human": 3
      },
      "needs_author_action": true
    },
    {
      "number": 3689,
      "author": "PastaPastaPasta",
      "score": 0.0,
      "unresolved_total": 0,
      "by_severity": {
        "high": 0,
        "medium": 0,
        "low": 0
      },
      "by_source": {
        "coderabbit": 0,
        "bot": 0,
        "human": 0
      },
      "needs_author_action": false
    },
    {
      "number": 3635,
      "author": "thepastaclaw",
      "score": 0.0,
      "unresolved_total": 0,
      "by_severity": {
        "high": 0,
        "medium": 0,
        "low": 0
      },
      "by_source": {
        "coderabbit": 0,
        "bot": 0,
        "human": 0
      },
      "needs_author_action": false
    },
    {
      "number": 3509,
      "author": "PastaPastaPasta",
      "score": 17.79643691057205,
      "unresolved_total": 1,
      "by_severity": {
        "high": 1,
        "medium": 0,
        "low": 0
      },
      "by_source": {
        "coderabbit": 0,
        "bot": 0,
        "human": 1
      },
      "needs_author_action": true
    },
    {
      "number": 3096,
      "author": "thepastaclaw",
      "score": 65.62065399715418,
      "unresolved_total": 4,
      "by_severity": {
        "high": 2,
        "medium": 2,
        "low": 0
      },
      "by_source": {
        "coderabbit": 2,
        "bot": 0,
        "human": 2
      },
      "needs_author_action": false
    },
    {
      "number": 3092,
      "author": "thepastaclaw",
      "score": 0.0,
      "unresolved_total": 0,
      "by_severity": {
        "high": 0,
        "medium": 0,
        "low": 0
      },
      "by_source": {
        "coderabbit": 0,
        "bot": 0,
        "human": 0
      },
      "needs_author_action": false
    },
    {
      "number": 3091,
      "author": "thepastaclaw",
      "score": 0.0,
      "unresolved_total": 0,
      "by_severity": {
        "high": 0,
        "medium": 0,
        "low": 0
      },
      "by_source": {
        "coderabbit": 0,
        "bot": 0,
        "human": 0
      },
      "needs_author_action": false
    },
    {
      "number": 3009,
      "author": "lklimek",
      "score": 0.0,
      "unresolved_total": 0,
      "by_severity": {
        "high": 0,
        "medium": 0,
        "low": 0
      },
      "by_source": {
        "coderabbit": 0,
        "bot": 0,
        "human": 0
      },
      "needs_author_action": false
    },
    {
      "number": 2993,
      "author": "lklimek",
      "score": 0.0,
      "unresolved_total": 0,
      "by_severity": {
        "high": 0,
        "medium": 0,
        "low": 0
      },
      "by_source": {
        "coderabbit": 0,
        "bot": 0,
        "human": 0
      },
      "needs_author_action": false
    },
    {
      "number": 2988,
      "author": "PastaPastaPasta",
      "score": 5.591706634105902,
      "unresolved_total": 1,
      "by_severity": {
        "high": 0,
        "medium": 1,
        "low": 0
      },
      "by_source": {
        "coderabbit": 0,
        "bot": 0,
        "human": 1
      },
      "needs_author_action": true
    },
    {
      "number": 3032,
      "author": "lklimek",
      "score": 0.0,
      "unresolved_total": 0,
      "by_severity": {
        "high": 0,
        "medium": 0,
        "low": 0
      },
      "by_source": {
        "coderabbit": 0,
        "bot": 0,
        "human": 0
      },
      "needs_author_action": false
    },
    {
      "number": 2795,
      "author": "lklimek",
      "score": 0.0,
      "unresolved_total": 0,
      "by_severity": {
        "high": 0,
        "medium": 0,
        "low": 0
      },
      "by_source": {
        "coderabbit": 0,
        "bot": 0,
        "human": 0
      },
      "needs_author_action": false
    },
    {
      "number": 2679,
      "author": "lklimek",
      "score": 0.0,
      "unresolved_total": 0,
      "by_severity": {
        "high": 0,
        "medium": 0,
        "low": 0
      },
      "by_source": {
        "coderabbit": 0,
        "bot": 0,
        "human": 0
      },
      "needs_author_action": false
    },
    {
      "number": 3770,
      "author": "Claudius-Maginificent",
      "score": 0.0,
      "unresolved_total": 0,
      "by_severity": {
        "high": 0,
        "medium": 0,
        "low": 0
      },
      "by_source": {
        "coderabbit": 0,
        "bot": 0,
        "human": 0
      },
      "needs_author_action": false
    },
    {
      "number": 1834,
      "author": "QuantumExplorer",
      "score": 0.0,
      "unresolved_total": 0,
      "by_severity": {
        "high": 0,
        "medium": 0,
        "low": 0
      },
      "by_source": {
        "coderabbit": 0,
        "bot": 0,
        "human": 0
      },
      "needs_author_action": false
    },
    {
      "number": 3417,
      "author": "QuantumExplorer",
      "score": 0.0,
      "unresolved_total": 0,
      "by_severity": {
        "high": 0,
        "medium": 0,
        "low": 0
      },
      "by_source": {
        "coderabbit": 0,
        "bot": 0,
        "human": 0
      },
      "needs_author_action": false
    },
    {
      "number": 3021,
      "author": "QuantumExplorer",
      "score": 0.0,
      "unresolved_total": 0,
      "by_severity": {
        "high": 0,
        "medium": 0,
        "low": 0
      },
      "by_source": {
        "coderabbit": 0,
        "bot": 0,
        "human": 0
      },
      "needs_author_action": false
    },
    {
      "number": 3557,
      "author": "QuantumExplorer",
      "score": 102.96461136647301,
      "unresolved_total": 11,
      "by_severity": {
        "high": 2,
        "medium": 9,
        "low": 0
      },
      "by_source": {
        "coderabbit": 2,
        "bot": 0,
        "human": 9
      },
      "needs_author_action": true
    },
    {
      "number": 3740,
      "author": "QuantumExplorer",
      "score": 62.703680374775885,
      "unresolved_total": 5,
      "by_severity": {
        "high": 5,
        "medium": 0,
        "low": 0
      },
      "by_source": {
        "coderabbit": 5,
        "bot": 0,
        "human": 0
      },
      "needs_author_action": true
    },
    {
      "number": 2392,
      "author": "shumkov",
      "score": 0.0,
      "unresolved_total": 0,
      "by_severity": {
        "high": 0,
        "medium": 0,
        "low": 0
      },
      "by_source": {
        "coderabbit": 0,
        "bot": 0,
        "human": 0
      },
      "needs_author_action": false
    },
    {
      "number": 3722,
      "author": "thepastaclaw",
      "score": 0.0,
      "unresolved_total": 0,
      "by_severity": {
        "high": 0,
        "medium": 0,
        "low": 0
      },
      "by_source": {
        "coderabbit": 0,
        "bot": 0,
        "human": 0
      },
      "needs_author_action": false
    },
    {
      "number": 2486,
      "author": "ogabrielides",
      "score": 0.0,
      "unresolved_total": 0,
      "by_severity": {
        "high": 0,
        "medium": 0,
        "low": 0
      },
      "by_source": {
        "coderabbit": 0,
        "bot": 0,
        "human": 0
      },
      "needs_author_action": false
    },
    {
      "number": 2518,
      "author": "shumkov",
      "score": 0.0,
      "unresolved_total": 0,
      "by_severity": {
        "high": 0,
        "medium": 0,
        "low": 0
      },
      "by_source": {
        "coderabbit": 0,
        "bot": 0,
        "human": 0
      },
      "needs_author_action": false
    },
    {
      "number": 2446,
      "author": "pshenmic",
      "score": 117.82345522741196,
      "unresolved_total": 5,
      "by_severity": {
        "high": 3,
        "medium": 2,
        "low": 0
      },
      "by_source": {
        "coderabbit": 5,
        "bot": 0,
        "human": 0
      },
      "needs_author_action": false
    }
  ]
}