{
  "date": "2026-06-19",
  "summary": {
    "open_prs": 51,
    "prs_needing_author_action": 17,
    "total_unresolved": 72
  },
  "per_author": [
    {
      "login": "PastaPastaPasta",
      "total_open_prs": 14,
      "clean_prs": 3,
      "dirty_prs": 4,
      "deferred_prs": 0,
      "draft_prs": 5,
      "stale_prs": 1,
      "ci_failing_prs": 1,
      "changes_requested_prs": 0,
      "awaiting_review": 0,
      "prs_needing_author_action": 4,
      "total_unresolved": 14,
      "total_score": 142.9714694987439,
      "oldest_stale_pr_days": 47.435462962962966
    },
    {
      "login": "QuantumExplorer",
      "total_open_prs": 9,
      "clean_prs": 1,
      "dirty_prs": 3,
      "deferred_prs": 2,
      "draft_prs": 2,
      "stale_prs": 0,
      "ci_failing_prs": 1,
      "changes_requested_prs": 0,
      "awaiting_review": 4,
      "prs_needing_author_action": 3,
      "total_unresolved": 9,
      "total_score": 93.22836132095158,
      "oldest_stale_pr_days": 24.579467592592593
    },
    {
      "login": "llbartekll",
      "total_open_prs": 3,
      "clean_prs": 0,
      "dirty_prs": 3,
      "deferred_prs": 0,
      "draft_prs": 0,
      "stale_prs": 0,
      "ci_failing_prs": 0,
      "changes_requested_prs": 0,
      "awaiting_review": 0,
      "prs_needing_author_action": 3,
      "total_unresolved": 5,
      "total_score": 53.89963381082332,
      "oldest_stale_pr_days": 17.66599537037037
    },
    {
      "login": "shumkov",
      "total_open_prs": 5,
      "clean_prs": 0,
      "dirty_prs": 1,
      "deferred_prs": 2,
      "draft_prs": 0,
      "stale_prs": 0,
      "ci_failing_prs": 0,
      "changes_requested_prs": 2,
      "awaiting_review": 3,
      "prs_needing_author_action": 3,
      "total_unresolved": 3,
      "total_score": 6.0,
      "oldest_stale_pr_days": 0.04518518518518518
    },
    {
      "login": "lklimek",
      "total_open_prs": 12,
      "clean_prs": 2,
      "dirty_prs": 1,
      "deferred_prs": 5,
      "draft_prs": 3,
      "stale_prs": 1,
      "ci_failing_prs": 0,
      "changes_requested_prs": 0,
      "awaiting_review": 1,
      "prs_needing_author_action": 2,
      "total_unresolved": 24,
      "total_score": 186.15292788371977,
      "oldest_stale_pr_days": 0.0
    },
    {
      "login": "ZocoLini",
      "total_open_prs": 3,
      "clean_prs": 1,
      "dirty_prs": 0,
      "deferred_prs": 0,
      "draft_prs": 1,
      "stale_prs": 0,
      "ci_failing_prs": 0,
      "changes_requested_prs": 1,
      "awaiting_review": 0,
      "prs_needing_author_action": 2,
      "total_unresolved": 12,
      "total_score": 115.07534746822341,
      "oldest_stale_pr_days": 23.447731481481483
    },
    {
      "login": "pshenmic",
      "total_open_prs": 1,
      "clean_prs": 0,
      "dirty_prs": 0,
      "deferred_prs": 0,
      "draft_prs": 0,
      "stale_prs": 1,
      "ci_failing_prs": 0,
      "changes_requested_prs": 0,
      "awaiting_review": 0,
      "prs_needing_author_action": 0,
      "total_unresolved": 5,
      "total_score": 118.32877654131049,
      "oldest_stale_pr_days": 505.65502314814813
    },
    {
      "login": "densmirnov",
      "total_open_prs": 1,
      "clean_prs": 1,
      "dirty_prs": 0,
      "deferred_prs": 0,
      "draft_prs": 0,
      "stale_prs": 0,
      "ci_failing_prs": 0,
      "changes_requested_prs": 0,
      "awaiting_review": 0,
      "prs_needing_author_action": 0,
      "total_unresolved": 0,
      "total_score": 0.0,
      "oldest_stale_pr_days": 0.0
    },
    {
      "login": "ogabrielides",
      "total_open_prs": 1,
      "clean_prs": 0,
      "dirty_prs": 0,
      "deferred_prs": 1,
      "draft_prs": 0,
      "stale_prs": 0,
      "ci_failing_prs": 0,
      "changes_requested_prs": 0,
      "awaiting_review": 0,
      "prs_needing_author_action": 0,
      "total_unresolved": 0,
      "total_score": 0.0,
      "oldest_stale_pr_days": 0.0
    },
    {
      "login": "thephez",
      "total_open_prs": 2,
      "clean_prs": 0,
      "dirty_prs": 0,
      "deferred_prs": 0,
      "draft_prs": 1,
      "stale_prs": 0,
      "ci_failing_prs": 1,
      "changes_requested_prs": 0,
      "awaiting_review": 0,
      "prs_needing_author_action": 0,
      "total_unresolved": 0,
      "total_score": 0.0,
      "oldest_stale_pr_days": 0.0
    }
  ],
  "per_pr": [
    {
      "number": 3573,
      "author": "shumkov",
      "score": 0.0,
      "unresolved_total": 0,
      "by_severity": {
        "high": 0,
        "medium": 0,
        "low": 0
      },
      "by_source": {
        "coderabbit": 0,
        "bot": 0,
        "human": 0
      },
      "needs_author_action": true
    },
    {
      "number": 3936,
      "author": "shumkov",
      "score": 6.0,
      "unresolved_total": 3,
      "by_severity": {
        "high": 0,
        "medium": 3,
        "low": 0
      },
      "by_source": {
        "coderabbit": 0,
        "bot": 0,
        "human": 3
      },
      "needs_author_action": true
    },
    {
      "number": 3935,
      "author": "QuantumExplorer",
      "score": 0.0,
      "unresolved_total": 0,
      "by_severity": {
        "high": 0,
        "medium": 0,
        "low": 0
      },
      "by_source": {
        "coderabbit": 0,
        "bot": 0,
        "human": 0
      },
      "needs_author_action": false
    },
    {
      "number": 3934,
      "author": "QuantumExplorer",
      "score": 2.0,
      "unresolved_total": 1,
      "by_severity": {
        "high": 0,
        "medium": 1,
        "low": 0
      },
      "by_source": {
        "coderabbit": 0,
        "bot": 0,
        "human": 1
      },
      "needs_author_action": true
    },
    {
      "number": 3938,
      "author": "thepastaclaw",
      "score": 0.0,
      "unresolved_total": 0,
      "by_severity": {
        "high": 0,
        "medium": 0,
        "low": 0
      },
      "by_source": {
        "coderabbit": 0,
        "bot": 0,
        "human": 0
      },
      "needs_author_action": false
    },
    {
      "number": 3828,
      "author": "Claudius-Maginificent",
      "score": 0.0,
      "unresolved_total": 0,
      "by_severity": {
        "high": 0,
        "medium": 0,
        "low": 0
      },
      "by_source": {
        "coderabbit": 0,
        "bot": 0,
        "human": 0
      },
      "needs_author_action": false
    },
    {
      "number": 3817,
      "author": "llbartekll",
      "score": 10.0,
      "unresolved_total": 2,
      "by_severity": {
        "high": 2,
        "medium": 0,
        "low": 0
      },
      "by_source": {
        "coderabbit": 0,
        "bot": 0,
        "human": 2
      },
      "needs_author_action": true
    },
    {
      "number": 3549,
      "author": "Claudius-Maginificent",
      "score": 155.1955714706474,
      "unresolved_total": 20,
      "by_severity": {
        "high": 0,
        "medium": 20,
        "low": 0
      },
      "by_source": {
        "coderabbit": 0,
        "bot": 0,
        "human": 20
      },
      "needs_author_action": false
    },
    {
      "number": 3841,
      "author": "shumkov",
      "score": 0.0,
      "unresolved_total": 0,
      "by_severity": {
        "high": 0,
        "medium": 0,
        "low": 0
      },
      "by_source": {
        "coderabbit": 0,
        "bot": 0,
        "human": 0
      },
      "needs_author_action": true
    },
    {
      "number": 3902,
      "author": "Claudius-Maginificent",
      "score": 30.95735641307238,
      "unresolved_total": 4,
      "by_severity": {
        "high": 4,
        "medium": 0,
        "low": 0
      },
      "by_source": {
        "coderabbit": 0,
        "bot": 0,
        "human": 4
      },
      "needs_author_action": true
    },
    {
      "number": 3910,
      "author": "QuantumExplorer",
      "score": 0.0,
      "unresolved_total": 0,
      "by_severity": {
        "high": 0,
        "medium": 0,
        "low": 0
      },
      "by_source": {
        "coderabbit": 0,
        "bot": 0,
        "human": 0
      },
      "needs_author_action": false
    },
    {
      "number": 3930,
      "author": "thepastaclaw",
      "score": 0.0,
      "unresolved_total": 0,
      "by_severity": {
        "high": 0,
        "medium": 0,
        "low": 0
      },
      "by_source": {
        "coderabbit": 0,
        "bot": 0,
        "human": 0
      },
      "needs_author_action": false
    },
    {
      "number": 3928,
      "author": "thephez",
      "score": 0.0,
      "unresolved_total": 0,
      "by_severity": {
        "high": 0,
        "medium": 0,
        "low": 0
      },
      "by_source": {
        "coderabbit": 0,
        "bot": 0,
        "human": 0
      },
      "needs_author_action": false
    },
    {
      "number": 3900,
      "author": "Claudius-Maginificent",
      "score": 0.0,
      "unresolved_total": 0,
      "by_severity": {
        "high": 0,
        "medium": 0,
        "low": 0
      },
      "by_source": {
        "coderabbit": 0,
        "bot": 0,
        "human": 0
      },
      "needs_author_action": true
    },
    {
      "number": 3712,
      "author": "ZocoLini",
      "score": 115.07534746822341,
      "unresolved_total": 12,
      "by_severity": {
        "high": 4,
        "medium": 8,
        "low": 0
      },
      "by_source": {
        "coderabbit": 4,
        "bot": 0,
        "human": 8
      },
      "needs_author_action": false
    },
    {
      "number": 3096,
      "author": "thepastaclaw",
      "score": 67.23849643239437,
      "unresolved_total": 4,
      "by_severity": {
        "high": 2,
        "medium": 2,
        "low": 0
      },
      "by_source": {
        "coderabbit": 2,
        "bot": 0,
        "human": 2
      },
      "needs_author_action": false
    },
    {
      "number": 3869,
      "author": "ZocoLini",
      "score": 0.0,
      "unresolved_total": 0,
      "by_severity": {
        "high": 0,
        "medium": 0,
        "low": 0
      },
      "by_source": {
        "coderabbit": 0,
        "bot": 0,
        "human": 0
      },
      "needs_author_action": true
    },
    {
      "number": 3923,
      "author": "QuantumExplorer",
      "score": 4.78300641066744,
      "unresolved_total": 2,
      "by_severity": {
        "high": 0,
        "medium": 2,
        "low": 0
      },
      "by_source": {
        "coderabbit": 0,
        "bot": 0,
        "human": 2
      },
      "needs_author_action": true
    },
    {
      "number": 3853,
      "author": "ZocoLini",
      "score": 0.0,
      "unresolved_total": 0,
      "by_severity": {
        "high": 0,
        "medium": 0,
        "low": 0
      },
      "by_source": {
        "coderabbit": 0,
        "bot": 0,
        "human": 0
      },
      "needs_author_action": true
    },
    {
      "number": 3669,
      "author": "thepastaclaw",
      "score": 0.0,
      "unresolved_total": 0,
      "by_severity": {
        "high": 0,
        "medium": 0,
        "low": 0
      },
      "by_source": {
        "coderabbit": 0,
        "bot": 0,
        "human": 0
      },
      "needs_author_action": false
    },
    {
      "number": 3692,
      "author": "Claudius-Maginificent",
      "score": 0.0,
      "unresolved_total": 0,
      "by_severity": {
        "high": 0,
        "medium": 0,
        "low": 0
      },
      "by_source": {
        "coderabbit": 0,
        "bot": 0,
        "human": 0
      },
      "needs_author_action": false
    },
    {
      "number": 3849,
      "author": "thephez",
      "score": 0.0,
      "unresolved_total": 0,
      "by_severity": {
        "high": 0,
        "medium": 0,
        "low": 0
      },
      "by_source": {
        "coderabbit": 0,
        "bot": 0,
        "human": 0
      },
      "needs_author_action": false
    },
    {
      "number": 3092,
      "author": "thepastaclaw",
      "score": 0.0,
      "unresolved_total": 0,
      "by_severity": {
        "high": 0,
        "medium": 0,
        "low": 0
      },
      "by_source": {
        "coderabbit": 0,
        "bot": 0,
        "human": 0
      },
      "needs_author_action": false
    },
    {
      "number": 3898,
      "author": "thepastaclaw",
      "score": 0.0,
      "unresolved_total": 0,
      "by_severity": {
        "high": 0,
        "medium": 0,
        "low": 0
      },
      "by_source": {
        "coderabbit": 0,
        "bot": 0,
        "human": 0
      },
      "needs_author_action": false
    },
    {
      "number": 3417,
      "author": "QuantumExplorer",
      "score": 0.0,
      "unresolved_total": 0,
      "by_severity": {
        "high": 0,
        "medium": 0,
        "low": 0
      },
      "by_source": {
        "coderabbit": 0,
        "bot": 0,
        "human": 0
      },
      "needs_author_action": false
    },
    {
      "number": 3635,
      "author": "thepastaclaw",
      "score": 0.0,
      "unresolved_total": 0,
      "by_severity": {
        "high": 0,
        "medium": 0,
        "low": 0
      },
      "by_source": {
        "coderabbit": 0,
        "bot": 0,
        "human": 0
      },
      "needs_author_action": false
    },
    {
      "number": 3509,
      "author": "PastaPastaPasta",
      "score": 19.401161256355238,
      "unresolved_total": 1,
      "by_severity": {
        "high": 1,
        "medium": 0,
        "low": 0
      },
      "by_source": {
        "coderabbit": 0,
        "bot": 0,
        "human": 1
      },
      "needs_author_action": true
    },
    {
      "number": 3650,
      "author": "lklimek",
      "score": 0.0,
      "unresolved_total": 0,
      "by_severity": {
        "high": 0,
        "medium": 0,
        "low": 0
      },
      "by_source": {
        "coderabbit": 0,
        "bot": 0,
        "human": 0
      },
      "needs_author_action": false
    },
    {
      "number": 2392,
      "author": "shumkov",
      "score": 0.0,
      "unresolved_total": 0,
      "by_severity": {
        "high": 0,
        "medium": 0,
        "low": 0
      },
      "by_source": {
        "coderabbit": 0,
        "bot": 0,
        "human": 0
      },
      "needs_author_action": false
    },
    {
      "number": 2486,
      "author": "ogabrielides",
      "score": 0.0,
      "unresolved_total": 0,
      "by_severity": {
        "high": 0,
        "medium": 0,
        "low": 0
      },
      "by_source": {
        "coderabbit": 0,
        "bot": 0,
        "human": 0
      },
      "needs_author_action": false
    },
    {
      "number": 2795,
      "author": "lklimek",
      "score": 0.0,
      "unresolved_total": 0,
      "by_severity": {
        "high": 0,
        "medium": 0,
        "low": 0
      },
      "by_source": {
        "coderabbit": 0,
        "bot": 0,
        "human": 0
      },
      "needs_author_action": false
    },
    {
      "number": 2679,
      "author": "lklimek",
      "score": 0.0,
      "unresolved_total": 0,
      "by_severity": {
        "high": 0,
        "medium": 0,
        "low": 0
      },
      "by_source": {
        "coderabbit": 0,
        "bot": 0,
        "human": 0
      },
      "needs_author_action": false
    },
    {
      "number": 2988,
      "author": "PastaPastaPasta",
      "score": 6.780536554426528,
      "unresolved_total": 1,
      "by_severity": {
        "high": 0,
        "medium": 1,
        "low": 0
      },
      "by_source": {
        "coderabbit": 0,
        "bot": 0,
        "human": 1
      },
      "needs_author_action": true
    },
    {
      "number": 3462,
      "author": "PastaPastaPasta",
      "score": 17.564482666795225,
      "unresolved_total": 3,
      "by_severity": {
        "high": 0,
        "medium": 3,
        "low": 0
      },
      "by_source": {
        "coderabbit": 0,
        "bot": 0,
        "human": 3
      },
      "needs_author_action": true
    },
    {
      "number": 3560,
      "author": "llbartekll",
      "score": 29.26703439118793,
      "unresolved_total": 2,
      "by_severity": {
        "high": 2,
        "medium": 0,
        "low": 0
      },
      "by_source": {
        "coderabbit": 0,
        "bot": 0,
        "human": 2
      },
      "needs_author_action": true
    },
    {
      "number": 3680,
      "author": "PastaPastaPasta",
      "score": 31.986792588772506,
      "unresolved_total": 5,
      "by_severity": {
        "high": 0,
        "medium": 5,
        "low": 0
      },
      "by_source": {
        "coderabbit": 0,
        "bot": 0,
        "human": 5
      },
      "needs_author_action": true
    },
    {
      "number": 3694,
      "author": "llbartekll",
      "score": 14.632599419635381,
      "unresolved_total": 1,
      "by_severity": {
        "high": 1,
        "medium": 0,
        "low": 0
      },
      "by_source": {
        "coderabbit": 0,
        "bot": 0,
        "human": 1
      },
      "needs_author_action": true
    },
    {
      "number": 3740,
      "author": "QuantumExplorer",
      "score": 81.04474956273135,
      "unresolved_total": 5,
      "by_severity": {
        "high": 5,
        "medium": 0,
        "low": 0
      },
      "by_source": {
        "coderabbit": 5,
        "bot": 0,
        "human": 0
      },
      "needs_author_action": true
    },
    {
      "number": 3787,
      "author": "densmirnov",
      "score": 0.0,
      "unresolved_total": 0,
      "by_severity": {
        "high": 0,
        "medium": 0,
        "low": 0
      },
      "by_source": {
        "coderabbit": 0,
        "bot": 0,
        "human": 0
      },
      "needs_author_action": false
    },
    {
      "number": 3792,
      "author": "QuantumExplorer",
      "score": 5.400605347552784,
      "unresolved_total": 1,
      "by_severity": {
        "high": 0,
        "medium": 1,
        "low": 0
      },
      "by_source": {
        "coderabbit": 0,
        "bot": 0,
        "human": 1
      },
      "needs_author_action": false
    },
    {
      "number": 3750,
      "author": "Claudius-Maginificent",
      "score": 0.0,
      "unresolved_total": 0,
      "by_severity": {
        "high": 0,
        "medium": 0,
        "low": 0
      },
      "by_source": {
        "coderabbit": 0,
        "bot": 0,
        "human": 0
      },
      "needs_author_action": false
    },
    {
      "number": 3133,
      "author": "thepastaclaw",
      "score": 0.0,
      "unresolved_total": 0,
      "by_severity": {
        "high": 0,
        "medium": 0,
        "low": 0
      },
      "by_source": {
        "coderabbit": 0,
        "bot": 0,
        "human": 0
      },
      "needs_author_action": false
    },
    {
      "number": 3689,
      "author": "PastaPastaPasta",
      "score": 0.0,
      "unresolved_total": 0,
      "by_severity": {
        "high": 0,
        "medium": 0,
        "low": 0
      },
      "by_source": {
        "coderabbit": 0,
        "bot": 0,
        "human": 0
      },
      "needs_author_action": false
    },
    {
      "number": 3091,
      "author": "thepastaclaw",
      "score": 0.0,
      "unresolved_total": 0,
      "by_severity": {
        "high": 0,
        "medium": 0,
        "low": 0
      },
      "by_source": {
        "coderabbit": 0,
        "bot": 0,
        "human": 0
      },
      "needs_author_action": false
    },
    {
      "number": 3009,
      "author": "lklimek",
      "score": 0.0,
      "unresolved_total": 0,
      "by_severity": {
        "high": 0,
        "medium": 0,
        "low": 0
      },
      "by_source": {
        "coderabbit": 0,
        "bot": 0,
        "human": 0
      },
      "needs_author_action": false
    },
    {
      "number": 2993,
      "author": "lklimek",
      "score": 0.0,
      "unresolved_total": 0,
      "by_severity": {
        "high": 0,
        "medium": 0,
        "low": 0
      },
      "by_source": {
        "coderabbit": 0,
        "bot": 0,
        "human": 0
      },
      "needs_author_action": false
    },
    {
      "number": 3032,
      "author": "lklimek",
      "score": 0.0,
      "unresolved_total": 0,
      "by_severity": {
        "high": 0,
        "medium": 0,
        "low": 0
      },
      "by_source": {
        "coderabbit": 0,
        "bot": 0,
        "human": 0
      },
      "needs_author_action": false
    },
    {
      "number": 1834,
      "author": "QuantumExplorer",
      "score": 0.0,
      "unresolved_total": 0,
      "by_severity": {
        "high": 0,
        "medium": 0,
        "low": 0
      },
      "by_source": {
        "coderabbit": 0,
        "bot": 0,
        "human": 0
      },
      "needs_author_action": false
    },
    {
      "number": 3021,
      "author": "QuantumExplorer",
      "score": 0.0,
      "unresolved_total": 0,
      "by_severity": {
        "high": 0,
        "medium": 0,
        "low": 0
      },
      "by_source": {
        "coderabbit": 0,
        "bot": 0,
        "human": 0
      },
      "needs_author_action": false
    },
    {
      "number": 2518,
      "author": "shumkov",
      "score": 0.0,
      "unresolved_total": 0,
      "by_severity": {
        "high": 0,
        "medium": 0,
        "low": 0
      },
      "by_source": {
        "coderabbit": 0,
        "bot": 0,
        "human": 0
      },
      "needs_author_action": false
    },
    {
      "number": 2446,
      "author": "pshenmic",
      "score": 118.32877654131049,
      "unresolved_total": 5,
      "by_severity": {
        "high": 3,
        "medium": 2,
        "low": 0
      },
      "by_source": {
        "coderabbit": 5,
        "bot": 0,
        "human": 0
      },
      "needs_author_action": false
    }
  ]
}